poremetrics/__init__.py
poremetrics/aspect_ratio.py
poremetrics/aspect_ratio_minimized.py
poremetrics/centroid.py
poremetrics/extract_largest_object.py
poremetrics/fill_mask_holes.py
poremetrics/find_area.py
poremetrics/invert_mask.py
poremetrics/perimeter.py
poremetrics/perimeter_coverage.py
poremetrics/points_to_mask.py
poremetrics/screen_portion.py
poremetrics/sharpness.py
poremetrics/surface_from_stitched.py
poremetrics/unfilled_ratio.py
poremetrics/validate_data.py
poremetrics-1.0.1.dist-info/licenses/LICENSE
poremetrics-1.0.1.dist-info/METADATA
poremetrics-1.0.1.dist-info/WHEEL
poremetrics-1.0.1.dist-info/top_level.txt
poremetrics-1.0.1.dist-info/RECORD
