Metadata-Version: 2.4
Name: poremetrics
Version: 1.0.1
Summary: Package for extracting features from segemented defects in defect initated fatigue.
Author-email: Anthony Lino <aml334@case.edu>
License-Expression: MIT
Project-URL: Homepage, https://github.com/cwru-sdle/pore-fatigue-metrics
Classifier: Programming Language :: Python :: 3
Classifier: Operating System :: OS Independent
Requires-Python: >=3.7
License-File: LICENSE
Requires-Dist: matplotlib
Requires-Dist: pandas
Requires-Dist: opencv-python
Dynamic: license-file
